kissdb/__init__.py
KissDB-0.0.0.dist-info/METADATA
KissDB-0.0.0.dist-info/WHEEL
KissDB-0.0.0.dist-info/top_level.txt
KissDB-0.0.0.dist-info/RECORD
